{
    "name": "butterfly",
    "points": {
        "a": [
            0,
            0
        ],
        "b": [
            20,
            0
        ],
        "c": [
            20,
            15
        ],
        "d": [
            0,
            15
        ],
        "e": [
            10,
            7.5
        ]
    },
    "vertices": [
        "e"
    ],
    "edges": {
        "loop1": [
            "e",
            "a",
            "d",
            "e"
        ],
        "loop2": [
            "e",
            "b",
            "c",
            "e"
        ]
    }
}
